{"nodes": [{"id": "d_desktop_x2_projet_integrateur_vue_src_utils_notifications_js", "label": "notifications.js", "file_type": "code", "source_file": "D:\\Desktop\\X2\\Projet Integrateur\\vue\\src\\utils\\notifications.js", "source_location": "L1"}, {"id": "notifications_requetenotifications", "label": "requeteNotifications()", "file_type": "code", "source_file": "D:\\Desktop\\X2\\Projet Integrateur\\vue\\src\\utils\\notifications.js", "source_location": "L5"}, {"id": "notifications_charger_notifications_temps_reel", "label": "charger_notifications_temps_reel()", "file_type": "code", "source_file": "D:\\Desktop\\X2\\Projet Integrateur\\vue\\src\\utils\\notifications.js", "source_location": "L23"}, {"id": "notifications_marquer_notification_lue", "label": "marquer_notification_lue()", "file_type": "code", "source_file": "D:\\Desktop\\X2\\Projet Integrateur\\vue\\src\\utils\\notifications.js", "source_location": "L42"}, {"id": "notifications_marquer_toutes_notifications_lues", "label": "marquer_toutes_notifications_lues()", "file_type": "code", "source_file": "D:\\Desktop\\X2\\Projet Integrateur\\vue\\src\\utils\\notifications.js", "source_location": "L49"}, {"id": "notifications_appliquer_action_notifications", "label": "appliquer_action_notifications()", "file_type": "code", "source_file": "D:\\Desktop\\X2\\Projet Integrateur\\vue\\src\\utils\\notifications.js", "source_location": "L56"}, {"id": "notifications_obtenir_route_notification", "label": "obtenir_route_notification()", "file_type": "code", "source_file": "D:\\Desktop\\X2\\Projet Integrateur\\vue\\src\\utils\\notifications.js", "source_location": "L63"}], "edges": [{"source": "d_desktop_x2_projet_integrateur_vue_src_utils_notifications_js", "target": "d_desktop_x2_projet_integrateur_vue_src_utils_config_ts", "relation": "imports_from", "confidence": "EXTRACTED", "source_file": "D:\\Desktop\\X2\\Projet Integrateur\\vue\\src\\utils\\notifications.js", "source_location": "L1", "weight": 1.0}, {"source": "d_desktop_x2_projet_integrateur_vue_src_utils_notifications_js", "target": "notifications_requetenotifications", "relation": "contains", "confidence": "EXTRACTED", "source_file": "D:\\Desktop\\X2\\Projet Integrateur\\vue\\src\\utils\\notifications.js", "source_location": "L5", "weight": 1.0}, {"source": "d_desktop_x2_projet_integrateur_vue_src_utils_notifications_js", "target": "notifications_charger_notifications_temps_reel", "relation": "contains", "confidence": "EXTRACTED", "source_file": "D:\\Desktop\\X2\\Projet Integrateur\\vue\\src\\utils\\notifications.js", "source_location": "L23", "weight": 1.0}, {"source": "d_desktop_x2_projet_integrateur_vue_src_utils_notifications_js", "target": "notifications_marquer_notification_lue", "relation": "contains", "confidence": "EXTRACTED", "source_file": "D:\\Desktop\\X2\\Projet Integrateur\\vue\\src\\utils\\notifications.js", "source_location": "L42", "weight": 1.0}, {"source": "d_desktop_x2_projet_integrateur_vue_src_utils_notifications_js", "target": "notifications_marquer_toutes_notifications_lues", "relation": "contains", "confidence": "EXTRACTED", "source_file": "D:\\Desktop\\X2\\Projet Integrateur\\vue\\src\\utils\\notifications.js", "source_location": "L49", "weight": 1.0}, {"source": "d_desktop_x2_projet_integrateur_vue_src_utils_notifications_js", "target": "notifications_appliquer_action_notifications", "relation": "contains", "confidence": "EXTRACTED", "source_file": "D:\\Desktop\\X2\\Projet Integrateur\\vue\\src\\utils\\notifications.js", "source_location": "L56", "weight": 1.0}, {"source": "d_desktop_x2_projet_integrateur_vue_src_utils_notifications_js", "target": "notifications_obtenir_route_notification", "relation": "contains", "confidence": "EXTRACTED", "source_file": "D:\\Desktop\\X2\\Projet Integrateur\\vue\\src\\utils\\notifications.js", "source_location": "L63", "weight": 1.0}, {"source": "notifications_marquer_notification_lue", "target": "notifications_requetenotifications", "relation": "calls", "confidence": "EXTRACTED", "source_file": "D:\\Desktop\\X2\\Projet Integrateur\\vue\\src\\utils\\notifications.js", "source_location": "L43", "weight": 1.0}, {"source": "notifications_marquer_toutes_notifications_lues", "target": "notifications_requetenotifications", "relation": "calls", "confidence": "EXTRACTED", "source_file": "D:\\Desktop\\X2\\Projet Integrateur\\vue\\src\\utils\\notifications.js", "source_location": "L50", "weight": 1.0}, {"source": "notifications_appliquer_action_notifications", "target": "notifications_requetenotifications", "relation": "calls", "confidence": "EXTRACTED", "source_file": "D:\\Desktop\\X2\\Projet Integrateur\\vue\\src\\utils\\notifications.js", "source_location": "L57", "weight": 1.0}], "raw_calls": [{"caller_nid": "notifications_requetenotifications", "callee": "fetch", "source_file": "D:\\Desktop\\X2\\Projet Integrateur\\vue\\src\\utils\\notifications.js", "source_location": "L6"}, {"caller_nid": "notifications_requetenotifications", "callee": "catch", "source_file": "D:\\Desktop\\X2\\Projet Integrateur\\vue\\src\\utils\\notifications.js", "source_location": "L16"}, {"caller_nid": "notifications_requetenotifications", "callee": "json", "source_file": "D:\\Desktop\\X2\\Projet Integrateur\\vue\\src\\utils\\notifications.js", "source_location": "L16"}, {"caller_nid": "notifications_requetenotifications", "callee": "json", "source_file": "D:\\Desktop\\X2\\Projet Integrateur\\vue\\src\\utils\\notifications.js", "source_location": "L20"}, {"caller_nid": "notifications_charger_notifications_temps_reel", "callee": "charger", "source_file": "D:\\Desktop\\X2\\Projet Integrateur\\vue\\src\\utils\\notifications.js", "source_location": "L38"}, {"caller_nid": "notifications_charger_notifications_temps_reel", "callee": "setInterval", "source_file": "D:\\Desktop\\X2\\Projet Integrateur\\vue\\src\\utils\\notifications.js", "source_location": "L39"}, {"caller_nid": "notifications_marquer_notification_lue", "callee": "encodeURIComponent", "source_file": "D:\\Desktop\\X2\\Projet Integrateur\\vue\\src\\utils\\notifications.js", "source_location": "L43"}, {"caller_nid": "notifications_marquer_notification_lue", "callee": "stringify", "source_file": "D:\\Desktop\\X2\\Projet Integrateur\\vue\\src\\utils\\notifications.js", "source_location": "L45"}, {"caller_nid": "notifications_marquer_toutes_notifications_lues", "callee": "stringify", "source_file": "D:\\Desktop\\X2\\Projet Integrateur\\vue\\src\\utils\\notifications.js", "source_location": "L52"}, {"caller_nid": "notifications_appliquer_action_notifications", "callee": "stringify", "source_file": "D:\\Desktop\\X2\\Projet Integrateur\\vue\\src\\utils\\notifications.js", "source_location": "L59"}]}